homevision_netio_controller/__init__.py
homevision_netio_controller/controller.py
homevision_netio_controller-0.1.1.dist-info/METADATA
homevision_netio_controller-0.1.1.dist-info/RECORD
homevision_netio_controller-0.1.1.dist-info/WHEEL
homevision_netio_controller-0.1.1.dist-info/top_level.txt
