Metadata-Version: 2.1
Name: homevision-netio-controller
Version: 0.1.1
Summary: A python api for controlling a homevision system via the netio interface.
Home-page: https://github.com/jackoson/homevision-netio-controller
Author: Jackoson
License: UNKNOWN
Platform: UNKNOWN
Classifier: Programming Language :: Python :: 3
Classifier: License :: OSI Approved :: MIT License
Classifier: Operating System :: OS Independent
